nuro_arm/__init__.py
nuro_arm/constants.py
nuro_arm/cube.py
nuro_arm/tk_utils.py
nuro_arm/transformation_utils.py
nuro_arm/assets/meshes/base.stl
nuro_arm/assets/meshes/base_rod_holder.stl
nuro_arm/assets/meshes/camera_with_holder.stl
nuro_arm/assets/meshes/finger_base.stl
nuro_arm/assets/meshes/finger_linkage.stl
nuro_arm/assets/meshes/finger_tip.stl
nuro_arm/assets/meshes/forearm.stl
nuro_arm/assets/meshes/hand.stl
nuro_arm/assets/meshes/swivel.stl
nuro_arm/assets/meshes/top_rod_holder.stl
nuro_arm/assets/meshes/upperarm.stl
nuro_arm/assets/meshes/wrist.stl
nuro_arm/assets/urdf/camera.urdf
nuro_arm/assets/urdf/camera_rod.urdf
nuro_arm/assets/urdf/cube.urdf
nuro_arm/assets/urdf/xarm.urdf
nuro_arm/camera/__init__.py
nuro_arm/camera/camera.py
nuro_arm/camera/camera_utils.py
nuro_arm/camera/capturer.py
nuro_arm/camera/gui.py
nuro_arm/images/bent_arm.png
nuro_arm/images/gripper_closed.png
nuro_arm/images/gripper_opened.png
nuro_arm/images/home.png
nuro_arm/robot/__init__.py
nuro_arm/robot/base_controller.py
nuro_arm/robot/motion_planner.py
nuro_arm/robot/pybullet_simulator.py
nuro_arm/robot/robot_arm.py
nuro_arm/robot/simulator_controller.py
nuro_arm/robot/xarm_controller.py
nuro_arm/scripts/__init__.py
nuro_arm/scripts/calibrate_camera.py
nuro_arm/scripts/calibrate_xarm.py
nuro_arm/scripts/generate_aruco_tags.py
nuro_arm/scripts/move_arm_with_gui.py
nuro_arm/scripts/record_movements.py
nuro_arm-0.0.5.dist-info/LICENSE
nuro_arm-0.0.5.dist-info/METADATA
nuro_arm-0.0.5.dist-info/WHEEL
nuro_arm-0.0.5.dist-info/entry_points.txt
nuro_arm-0.0.5.dist-info/top_level.txt
nuro_arm-0.0.5.dist-info/RECORD
