Metadata-Version: 2.1
Name: nuro-arm
Version: 0.0.5
Summary: NURO Arm: Accessible Robotics Educational Platform
Home-page: https://github.com/dmklee/nuro-arm
Author: David Klee
Author-email: David Klee <klee.d@northeastern.edu>
License: MIT License
Project-URL: Homepage, https://github.com/dmklee/nuro-arm
Project-URL: Bug Tracker, https://github.com/dmklee/nuro-arm/issues
Keywords: robotics,educational-project,low-cost-robot,robotic-manipulation
Classifier: Programming Language :: Python :: 3
Classifier: License :: OSI Approved :: MIT License
Classifier: Operating System :: OS Independent
Requires-Python: >3.6.0
License-File: LICENSE
Requires-Dist: numpy
Requires-Dist: scipy
Requires-Dist: pillow
Requires-Dist: pybullet (>=3.1.7)
Requires-Dist: hidapi ; platform_system == "Darwin"
Requires-Dist: easyhid ; platform_system == "Linux"
Requires-Dist: hid ; platform_system == "Windows"
Provides-Extra: all
Requires-Dist: opencv-contrib-python ; extra == 'all'
